test_unstructured/__init__.py
test_unstructured/test_utils.py
test_unstructured/unit_utils.py
test_unstructured/chunking/__init__.py
test_unstructured/chunking/test_base.py
test_unstructured/chunking/test_basic.py
test_unstructured/chunking/test_dispatch.py
test_unstructured/chunking/test_html_output.py
test_unstructured/chunking/test_title.py
test_unstructured/cleaners/__init__.py
test_unstructured/cleaners/test_core.py
test_unstructured/cleaners/test_extract.py
test_unstructured/cleaners/test_translate.py
test_unstructured/common/__init__.py
test_unstructured/common/test_html_table.py
test_unstructured/documents/__init__.py
test_unstructured/documents/test_coordinates.py
test_unstructured/documents/test_elements.py
test_unstructured/documents/test_mappings.py
test_unstructured/documents/test_ontology_to_unstructured_parsing.py
test_unstructured/embed/__init__.py
test_unstructured/embed/test_mixedbreadai.py
test_unstructured/embed/test_octoai.py
test_unstructured/embed/test_openai.py
test_unstructured/embed/test_vertexai.py
test_unstructured/embed/test_voyageai.py
test_unstructured/file_utils/__init__.py
test_unstructured/file_utils/test_encoding.py
test_unstructured/file_utils/test_file_conversion.py
test_unstructured/file_utils/test_filetype.py
test_unstructured/file_utils/test_model.py
test_unstructured/metrics/__init__.py
test_unstructured/metrics/test_element_type.py
test_unstructured/metrics/test_evaluate.py
test_unstructured/metrics/test_table_alignment.py
test_unstructured/metrics/test_table_detection_metrics.py
test_unstructured/metrics/test_table_formats.py
test_unstructured/metrics/test_table_structure.py
test_unstructured/metrics/test_text_extraction.py
test_unstructured/metrics/test_utils.py
test_unstructured/nlp/__init__.py
test_unstructured/nlp/mock_nltk.py
test_unstructured/nlp/test_partition.py
test_unstructured/nlp/test_tokenize.py
test_unstructured/partition/__init__.py
test_unstructured/partition/conftest.py
unstructured-0.18.27.dist-info/licenses/LICENSE.md
unstructured-0.18.27.dist-info/METADATA
unstructured-0.18.27.dist-info/WHEEL
unstructured-0.18.27.dist-info/top_level.txt
unstructured-0.18.27.dist-info/RECORD
